model_selection.py
ml_model_selection-1.0.0.dist-info/LICENSE
ml_model_selection-1.0.0.dist-info/METADATA
ml_model_selection-1.0.0.dist-info/WHEEL
ml_model_selection-1.0.0.dist-info/top_level.txt
ml_model_selection-1.0.0.dist-info/RECORD
