Metadata-Version: 2.1
Name: ml-model-selection
Version: 1.0.0
Summary: Library for the selection of machine learning models
Home-page: https://github.com/EnricoPittini/model-selection
Author: Enrico Pittini
Author-email: pittinienrico@hotmail.it
License: MIT
Platform: UNKNOWN
Classifier: Programming Language :: Python :: 3
Classifier: License :: OSI Approved :: MIT License
Classifier: Operating System :: OS Independent
License-File: LICENSE
Requires-Dist: numpy
Requires-Dist: matplotlib
Requires-Dist: sklearn
